mlx_video/__init__.py
mlx_video/convert.py
mlx_video/generate.py
mlx_video/generate_av.py
mlx_video/postprocess.py
mlx_video/text_projection.py
mlx_video/utils.py
mlx_video/version.py
mlx_video/conditioning/__init__.py
mlx_video/conditioning/latent.py
mlx_video/models/__init__.py
mlx_video/models/ltx/__init__.py
mlx_video/models/ltx/adaln.py
mlx_video/models/ltx/attention.py
mlx_video/models/ltx/config.py
mlx_video/models/ltx/feed_forward.py
mlx_video/models/ltx/ltx.py
mlx_video/models/ltx/rope.py
mlx_video/models/ltx/text_encoder.py
mlx_video/models/ltx/text_projection.py
mlx_video/models/ltx/transformer.py
mlx_video/models/ltx/upsampler.py
mlx_video/models/ltx/audio_vae/__init__.py
mlx_video/models/ltx/audio_vae/attention.py
mlx_video/models/ltx/audio_vae/audio_vae.py
mlx_video/models/ltx/audio_vae/causal_conv_2d.py
mlx_video/models/ltx/audio_vae/causality_axis.py
mlx_video/models/ltx/audio_vae/downsample.py
mlx_video/models/ltx/audio_vae/normalization.py
mlx_video/models/ltx/audio_vae/ops.py
mlx_video/models/ltx/audio_vae/resnet.py
mlx_video/models/ltx/audio_vae/upsample.py
mlx_video/models/ltx/audio_vae/vocoder.py
mlx_video/models/ltx/video_vae/__init__.py
mlx_video/models/ltx/video_vae/convolution.py
mlx_video/models/ltx/video_vae/decoder.py
mlx_video/models/ltx/video_vae/encoder.py
mlx_video/models/ltx/video_vae/ops.py
mlx_video/models/ltx/video_vae/resnet.py
mlx_video/models/ltx/video_vae/sampling.py
mlx_video/models/ltx/video_vae/tiling.py
mlx_video/models/ltx/video_vae/video_vae.py
mlx_video_with_audio-0.1.3.dist-info/licenses/LICENSE
mlx_video_with_audio-0.1.3.dist-info/METADATA
mlx_video_with_audio-0.1.3.dist-info/WHEEL
mlx_video_with_audio-0.1.3.dist-info/entry_points.txt
mlx_video_with_audio-0.1.3.dist-info/top_level.txt
mlx_video_with_audio-0.1.3.dist-info/RECORD
