Metadata-Version: 2.4
Name: mlx-video-with-audio
Version: 0.1.3
Summary: Generate videos with synchronized audio on Apple Silicon using MLX. Supports text-to-video (T2V) and image-to-video (I2V) with LTX-2.
Author-email: Prince Canuma <prince.gdt@gmail.com>
License: MIT
Project-URL: Homepage, https://github.com/james-see/mlx-video-with-audio
Project-URL: Repository, https://github.com/james-see/mlx-video-with-audio
Project-URL: Issues, https://github.com/james-see/mlx-video-with-audio/issues
Keywords: mlx,video-generation,audio-generation,apple-silicon,text-to-video,image-to-video,ltx,diffusion,ai,machine-learning
Classifier: Development Status :: 4 - Beta
Classifier: Intended Audience :: Developers
Classifier: License :: OSI Approved :: MIT License
Classifier: Programming Language :: Python :: 3.10
Classifier: Programming Language :: Python :: 3.11
Classifier: Programming Language :: Python :: 3.12
Classifier: Programming Language :: Python :: 3.13
Requires-Python: >=3.11
License-File: LICENSE
Requires-Dist: mlx>=0.22.0
Requires-Dist: numpy
Requires-Dist: safetensors
Requires-Dist: huggingface_hub
Requires-Dist: transformers[tokenizers]
Requires-Dist: tqdm
Requires-Dist: opencv-python>=4.12.0.88
Requires-Dist: Pillow>=10.3.0
Requires-Dist: mlx-vlm
Requires-Dist: soundfile>=0.12.0
Provides-Extra: dev
Requires-Dist: pytest; extra == "dev"
Dynamic: license-file
